{
  "announcements": [
    {
      "version": "2.0.0",
      "date": "2026-03-31",
      "title": "参考成熟独游重构终端界面",
      "summary": "整包界面改为更接近 Steam 成熟独立 RPG 的终端风：更克制的线条、更干净的排版、更统一的三栏壳体与窗格语言。",
      "notes": [
        "主界面、事件、战斗、建档与菜单统一收进一套更成熟的终端壳体，不再有首页化、页游大厅化的展示层。",
        "整体视觉从厚重页游金属框继续收敛到更精致的深色线条系统：低饱和、直角、细边框、弱阴影、强排版。",
        "左中右三栏的层级进一步明确：左侧角色本体，中间叙事与命令，右侧风闻、任务、关系与地点上下文。",
        "背包、技能、地图、商店和公告窗口重新整理为更像成熟独游的双栏窗格，减少噪音装饰，强化信息阅读与操作效率。",
        "按钮、分页、快捷栏、抽屉、列表高亮、品质边框与浮动提示全部重新校准成更克制的终端风。"
      ]
    },
    {
      "version": "1.9.0",
      "date": "2026-03-31",
      "title": "重构为简约 MUD 终端界面，打开即进入游戏",
      "summary": "这一版不再强调首页或厚重页游门面，而是把整套项目重构成打开即进入游戏的三栏终端界面：弱装饰、强排版、直角细线、深色低饱和，围绕叙事、状态和决策来组织全部信息。",
      "notes": [
        "取消默认进入主菜单的流程，加载完成后如果存在存档会直接恢复到当前事件或地图，没有存档则直接进入创建角色界面。",
        "主游戏界面重构为三栏 MUD 终端布局：左侧角色本体区、中央视图叙事区、右侧任务与风闻上下文区。",
        "统一新的视觉 token：深灰黑底、冷灰线框、旧纸色正文、暗金强调、全部直角、极轻阴影。",
        "底部命令栏重新设计为轻量命令按钮组，人物、背包、技能、地图、商店、公告与存档现在作为系统命令而不是首页入口。",
        "左右抽屉保留，但改成更窄的系统栏，只承担角色内务和世界系统入口，不再抢占主界面视觉中心。",
        "创建角色、事件、战斗、结局与主场景全部统一为同一套终端式 UI 语言，删去展示页式 banner 和过厚装饰。",
        "弹窗与仓库系统继续保留现有功能，但整体皮肤收束为更克制的直角窗格与信息面板风格。"
      ]
    },
    {
      "version": "1.8.0",
      "date": "2026-03-31",
      "title": "补齐装备格子框体、拖拽换装、技能快捷栏与分页仓库",
      "summary": "这一版把项目继续往传统页游 / DNF 风格推进，重点落在装备格子视觉、品质边框、拖拽交互、技能快捷栏和分页仓库上，让主界面与弹窗系统都更像真正的长期运营页游客户端。",
      "notes": [
        "新增更接近 DNF 的装备格子背景框体，个人信息面板和左侧穿戴摘要都改成更明确的槽位视觉。",
        "新增品质边框与高亮规则，装备、背包条目、商店条目和快捷栏条目会根据普通/精良/稀有/史诗/传说显示不同边框层次。",
        "新增拖拽换装：可以从背包里直接把装备拖到个人信息窗口的武器 / 护甲 / 饰品槽位进行穿戴。",
        "新增技能快捷栏：角色现在保存四个快捷技能槽，技能窗口内支持拖拽分配，主界面中央下方也会显示当前快捷栏。",
        "背包与商城加入分页仓库结构，避免中后期物品过多时一屏过长，浏览和预览更接近传统页游仓库体验。",
        "继续强化 UMD 直角金属线条风，窗口内容区、列表项、格子框体与分割线更硬朗、更统一。"
      ]
    },
    {
      "version": "1.7.0",
      "date": "2026-03-31",
      "title": "强化直角线条 UI，并将背包等弹窗收成 DNF 风格",
      "summary": "这次更新主要不是加新系统，而是把项目现有窗口和界面皮肤统一收紧成更硬朗的 UMD 直角金属风，重点提升背包、商场、技能等游戏内弹窗的观感与信息阅读效率。",
      "notes": [
        "整体 UI 再次强化为直角硬线条风格，窗口、按钮、标签、面板和提示框统一去圆角，边框与暗金属层次更明确。",
        "背包窗口改为更接近 DNF 的仓库式分栏布局，新增分类标签、图标位、强标题条和更清晰的物品列表层级。",
        "商场窗口同步收成 DNF 向货架界面，按装备、药品、其他分栏，物品预览与购买信息更直观。",
        "技能窗口新增招式 / 心法分类标签，统一到和背包、商场一致的金属框体与右侧预览信息面板。",
        "悬停 tooltip 与右侧预览面板继续强化，物品品质、用途、穿戴变化与属性阅读更接近传统页游 RPG 面板。",
        "修正品质类名映射问题，white/green/blue/purple/orange 和 common/uncommon/rare/epic/legendary 现在都能正确显示对应颜色。"
      ]
    },
    {
      "version": "1.6.0",
      "date": "2026-03-31",
      "title": "主菜单与结局页统一为 UMD 线条界面",
      "summary": "主菜单和结局页不再保留独立展示页风格，全部切到与主游戏界面一致的三列式 UMD 线条布局。",
      "notes": [
        "主菜单改为真正的游戏内主菜单，使用左信息列 / 中央操作区 / 右情报列的统一 UMD 线条界面。",
        "主菜单新增存档概览、启动须知、首发内容卡片和世界/版本情报，不再出现官网式大标题英雄区。",
        "结局页改为真正的游戏内结算界面，中央展示结局标题、剧情总结与后续选择。",
        "结局页左列显示人物状态和结局档案，右列显示结局说明、推荐后续和当前记录。",
        "结局页继续保留左右小三角抽屉，可直接打开个人信息、背包、技能、地图、商场、公告和后台。",
        "修复主菜单阶段打开个人信息或后台窗口可能报错的问题，在未建角状态下会显示空状态提示。"
      ]
    },
    {
      "version": "1.5.0",
      "date": "2026-03-31",
      "title": "创建角色、事件与战斗页统一为 UMD 线条界面",
      "summary": "创建角色页、事件页、战斗页全部切到和主游戏界面一致的全屏 UMD 线条布局，左右侧三角抽屉与游戏内窗口保持统一。",
      "notes": [
        "创建角色页改为纯游戏内建档界面，采用左档案列 / 中央创建区 / 右路线情报列的三段式布局。",
        "创建角色页加入出身属性预览、天赋说明、开局携带和当前选择摘要，建档前就能看到角色走向。",
        "事件页改为统一 UMD 线条事件界面，剧情描述、收益提示和选项区集中在中央主面板。",
        "事件页左列显示头像、气血蓝条与基础属性，右列显示角色状态、势力声望与事件说明。",
        "战斗页改为统一 UMD 线条战斗界面，中央显示对阵、战斗日志和操作区，右列显示敌方概要和作战提示。",
        "事件页与战斗页继续保留左右侧小三角抽屉，可拉出个人信息、背包、技能、地图、商场，以及公告和后台。",
        "新场景继续复用暗金属 / DNF 向弹窗皮肤和统一方角边框风格。"
      ]
    },
    {
      "version": "1.4.0",
      "date": "2026-03-31",
      "title": "UMD 线条主界面改版",
      "summary": "移除站点式头部，主界面改为纯游戏界面；左上头像与蓝条、左侧基础属性、左右三角抽屉菜单全部接入。",
      "notes": [
        "删除首页顶部游戏名与说明栏，进入站点后整个区域都作为游戏界面使用。",
        "主界面改为 UMD 线条风格，统一取消圆角，强化边框、分割线和硬朗金属感。",
        "左上角加入头像、角色名、气血条与内力蓝条，作为游戏状态核心显示。",
        "左侧新增基础属性列，实时展示基础属性与最终战斗属性。",
        "主界面改为左属性列 / 中央场景区 / 右情报列的三段式布局。",
        "左右两侧加入小三角抽屉，拉出后以竖排显示个人信息、背包、技能、地图、商场。",
        "右侧抽屉保留公告与后台入口，仍然以游戏内窗口方式打开。",
        "整体窗口与浮动提示继续沿用统一的 DNF 向暗金属弹窗皮肤。"
      ]
    },
    {
      "version": "1.3.0",
      "date": "2026-03-30",
      "title": "统一物品库、装备库与系统三角菜单",
      "summary": "本次更新把项目从单纯页游骨架，推进为具备统一数据仓、装备联动和版本公告体系的正式游戏界面。",
      "notes": [
        "新增统一道具库 itemLibrary 与装备库 equipmentLibrary，作为全项目物品定义源。",
        "重构玩家背包存储，装备采用实例化记录，支持穿戴/卸下同步与后续强化扩展。",
        "新增人物属性三层结构：基础属性、装备加成、最终战斗属性。",
        "装备穿脱后会自动重算攻击、防御、身法、气血和内力，不再手工加减。",
        "右上角加入系统侧拉三角，可在游戏内打开公告与后台窗口。",
        "公告系统接入版本记录，每个版本更新内容都会写入游戏内公告面板。",
        "个人信息 / 背包 / 商城 / 技能 / 地图五大窗口继续保持统一 DNF 风格。",
        "背包、商城、人物装备栏支持悬停预览，并带有独立信息面板与浮动提示。"
      ]
    },
    {
      "version": "1.2.0",
      "date": "2026-03-30",
      "title": "主界面页游化改版",
      "summary": "首页从展示页改为真正的页游主界面，补齐底部功能栏和统一弹窗体系。",
      "notes": [
        "主界面改为顶部状态栏、中央游戏区、右侧情报区、底部功能栏布局。",
        "新增个人信息、背包、商城、技能、地图五个并排按钮。",
        "弹窗皮肤统一为暗金属 / DNF 风格。",
        "增加装备与商品的基础悬停预览面板。"
      ]
    },
    {
      "version": "1.1.0",
      "date": "2026-03-30",
      "title": "仓库门面与版本页完善",
      "summary": "统一仓库口径，补齐最终版 README、版本页和 GitHub 发布说明。",
      "notes": [
        "统一仓库名为 transmigrator-wuxia。",
        "新增版本页与版本元信息文件。",
        "README 增加徽章、发布页截图区和正式项目说明。"
      ]
    },
    {
      "version": "1.0.0",
      "date": "2026-03-30",
      "title": "正式项目初版",
      "summary": "完成可直接推送 GitHub 的正式静态项目包。",
      "notes": [
        "建立 Phaser + UMD 页游工程结构。",
        "接入 GitHub Pages 自动部署工作流。",
        "完成武侠世界基础数据、主线、战斗和存档能力。"
      ]
    }
  ]
}